setup.cfg
setup.py
gtimer/__init__.py
gtimer/util.py
gtimer.egg-info/PKG-INFO
gtimer.egg-info/SOURCES.txt
gtimer.egg-info/dependency_links.txt
gtimer.egg-info/not-zip-safe
gtimer.egg-info/top_level.txt
gtimer/disabled/__init__.py
gtimer/disabled/private.py
gtimer/disabled/public.py
gtimer/local/__init__.py
gtimer/local/exceptions.py
gtimer/local/loop.py
gtimer/local/merge.py
gtimer/local/report.py
gtimer/local/stack.py
gtimer/local/timer.py
gtimer/local/times.py
gtimer/local/util.py
gtimer/private/__init__.py
gtimer/private/collapse.py
gtimer/private/const.py
gtimer/private/focus.py
gtimer/private/loop.py
gtimer/private/timedloop.py
gtimer/private/times.py
gtimer/public/__init__.py
gtimer/public/io.py
gtimer/public/report.py
gtimer/public/timedloop.py
gtimer/public/timer.py