Metadata-Version: 1.1
Name: gtimer
Version: 1.0.0b3
Summary: A global Python timer
Home-page: http://github.com/astooke/gtimer
Author: Adam Stooke
Author-email: adam.stooke@gmail.com
License: MIT
Platform: UNKNOWN
Classifier: Development Status :: 4 - Beta
Classifier: Programming Language :: Python :: 2
